pywget/__init__.py
pywget/__main__.py
pywget/pywget.py
pywget_cranky-1.3.2.dist-info/METADATA
pywget_cranky-1.3.2.dist-info/WHEEL
pywget_cranky-1.3.2.dist-info/entry_points.txt
pywget_cranky-1.3.2.dist-info/top_level.txt
pywget_cranky-1.3.2.dist-info/RECORD
