Metadata-Version: 2.1
Name: pywget-cranky
Version: 1.3.2
Platform: win
Requires-Dist: click (>=8.0)
Requires-Dist: python-dateutil (>=2.8)
Requires-Dist: requests (>=2.25)
Requires-Dist: tqdm (>=4.5)
